{"notcurses-demo":{"spec":"ixethbcgrwuvlfsjo","TERM":"alacritty","rows":"52","cols":"87","runs":{"intro":{"bytes":"6438725","frames":"148","ns":"3016910816"},"xray":{"bytes":"12928477","frames":"302","ns":"5038090217"},"eagle":{"bytes":"12037895","frames":"158","ns":"2831668567"},"trans":{"bytes":"1843078","frames":"633","ns":"16033000667"},"highcon":{"bytes":"88973250","frames":"2218","ns":"1176638712"},"box":{"bytes":"3323628","frames":"51","ns":"3156556554"},"chunli":{"bytes":"1397762","frames":"53","ns":"5396528814"},"grid":{"bytes":"113773206","frames":"768","ns":"1563824347"},"reel":{"bytes":"675269","frames":"24","ns":"5192571376"},"whiteout":{"bytes":"7823429","frames":"62907","ns":"10000970812"},"uniblock":{"bytes":"892912","frames":"70","ns":"23386297291"},"view":{"bytes":"78041076","frames":"753","ns":"19580230234"},"luigi":{"bytes":"1665961","frames":"120","ns":"1792202243"},"fallin'":{"bytes":"1175563","frames":"425","ns":"4778180416"},"sliders":{"bytes":"872420","frames":"331","ns":"5094473819"},"jungle":{"bytes":"688587","frames":"701","ns":"5007399168"},"outro":{"bytes":"19917758","frames":"434","ns":"13007981160"},}}}
