{"notcurses-demo":{"spec":"ixethbcgrwuvlfsjo","TERM":"alacritty","rows":"52","cols":"150","runs":{"intro":{"bytes":"14970326","frames":"148","ns":"3024022231"},"xray":{"bytes":"18348979","frames":"302","ns":"5036315727"},"eagle":{"bytes":"20757282","frames":"221","ns":"3049503086"},"trans":{"bytes":"3958860","frames":"633","ns":"16103726521"},"highcon":{"bytes":"264185588","frames":"3825","ns":"3855089639"},"box":{"bytes":"5268034","frames":"51","ns":"3188937124"},"chunli":{"bytes":"1412273","frames":"53","ns":"5401989581"},"grid":{"bytes":"194601711","frames":"768","ns":"2855726168"},"reel":{"bytes":"1961519","frames":"31","ns":"5009555900"},"whiteout":{"bytes":"12596447","frames":"36085","ns":"10001180084"},"uniblock":{"bytes":"936660","frames":"70","ns":"23394874870"},"view":{"bytes":"113339165","frames":"753","ns":"19582483000"},"luigi":{"bytes":"2992500","frames":"183","ns":"1516505738"},"fallin'":{"bytes":"1860851","frames":"469","ns":"4858667556"},"sliders":{"bytes":"2308613","frames":"397","ns":"5170464882"},"jungle":{"bytes":"736769","frames":"701","ns":"5007305406"},"outro":{"bytes":"31001827","frames":"434","ns":"13018919947"},}}}
