{"notcurses-demo":{"spec":"ixethbcgrwuvlfsjo","TERM":"kitty-direct","rows":"52","cols":"131","runs":{"intro":{"bytes":"12737805","frames":"148","ns":"3021594198"},"xray":{"bytes":"17587347","frames":"302","ns":"5035928801"},"eagle":{"bytes":"18119923","frames":"202","ns":"2979868128"},"trans":{"bytes":"4728979","frames":"633","ns":"16116612028"},"highcon":{"bytes":"202254983","frames":"3340","ns":"4000616727"},"box":{"bytes":"4682137","frames":"51","ns":"3150248433"},"chunli":{"bytes":"1391853","frames":"53","ns":"5394740739"},"grid":{"bytes":"170397198","frames":"768","ns":"2869637451"},"reel":{"bytes":"1608522","frames":"23","ns":"5093330171"},"whiteout":{"bytes":"11140230","frames":"40015","ns":"10001733811"},"uniblock":{"bytes":"914244","frames":"70","ns":"23417612448"},"view":{"bytes":"112634710","frames":"753","ns":"19571034043"},"luigi":{"bytes":"2576999","frames":"164","ns":"1568288147"},"fallin'":{"bytes":"1741792","frames":"529","ns":"5019021156"},"sliders":{"bytes":"1860246","frames":"377","ns":"5164265213"},"outro":{"bytes":"29078726","frames":"434","ns":"13017371083"},}}}
