{"notcurses-demo":{"spec":"ixethbcgrwuvlfsjo","TERM":"kitty-direct","rows":"52","cols":"97","runs":{"intro":{"bytes":"8000983","frames":"148","ns":"3019682712"},"xray":{"bytes":"14038479","frames":"302","ns":"5035986653"},"eagle":{"bytes":"13419634","frames":"168","ns":"2812127848"},"trans":{"bytes":"1654885","frames":"633","ns":"16034766109"},"highcon":{"bytes":"111236719","frames":"2473","ns":"2220327808"},"box":{"bytes":"3632193","frames":"51","ns":"3137446693"},"chunli":{"bytes":"1393844","frames":"53","ns":"5396956188"},"grid":{"bytes":"126397729","frames":"768","ns":"2185229172"},"reel":{"bytes":"659337","frames":"26","ns":"5102209722"},"whiteout":{"bytes":"8476598","frames":"54292","ns":"10001252605"},"uniblock":{"bytes":"894304","frames":"70","ns":"23411602436"},"view":{"bytes":"86136321","frames":"753","ns":"19569181705"},"luigi":{"bytes":"1866192","frames":"130","ns":"1716176609"},"fallin'":{"bytes":"1324830","frames":"455","ns":"4758638799"},"sliders":{"bytes":"869388","frames":"329","ns":"5103157775"},"outro":{"bytes":"22088467","frames":"434","ns":"13007507061"},}}}
