{"notcurses-demo":{"spec":"ixethbcgrwuvlfsjo","TERM":"kitty-direct","rows":"52","cols":"120","runs":{"intro":{"bytes":"11309717","frames":"148","ns":"3021093467"},"xray":{"bytes":"15263559","frames":"302","ns":"5035921191"},"eagle":{"bytes":"16579001","frames":"191","ns":"2912942069"},"trans":{"bytes":"4055717","frames":"633","ns":"16097223931"},"highcon":{"bytes":"170107612","frames":"3060","ns":"3383424364"},"box":{"bytes":"4342850","frames":"51","ns":"3157723475"},"chunli":{"bytes":"1411055","frames":"53","ns":"5400143819"},"grid":{"bytes":"155329080","frames":"768","ns":"2663718011"},"reel":{"bytes":"1372386","frames":"32","ns":"5200164235"},"whiteout":{"bytes":"10192252","frames":"43695","ns":"10000819142"},"uniblock":{"bytes":"908982","frames":"70","ns":"23415170197"},"view":{"bytes":"93634982","frames":"753","ns":"19570074440"},"luigi":{"bytes":"2345850","frames":"153","ns":"1601484794"},"fallin'":{"bytes":"1583125","frames":"472","ns":"4940166233"},"sliders":{"bytes":"1434333","frames":"361","ns":"5142254380"},"outro":{"bytes":"25565856","frames":"434","ns":"13006799132"},}}}
