{"notcurses-demo":{"spec":"ixethbcgrwuvlfsjo","TERM":"kitty-direct","rows":"52","cols":"114","runs":{"intro":{"bytes":"10484088","frames":"148","ns":"3021049469"},"xray":{"bytes":"14911954","frames":"302","ns":"5035846996"},"eagle":{"bytes":"15743969","frames":"185","ns":"2892868061"},"trans":{"bytes":"3324823","frames":"633","ns":"16065191774"},"highcon":{"bytes":"153706857","frames":"2907","ns":"3068905951"},"box":{"bytes":"4157894","frames":"51","ns":"3146668959"},"chunli":{"bytes":"1411135","frames":"53","ns":"5397310372"},"grid":{"bytes":"147827175","frames":"768","ns":"2515692058"},"reel":{"bytes":"1234523","frames":"29","ns":"5087650598"},"whiteout":{"bytes":"9698780","frames":"45752","ns":"10001398676"},"uniblock":{"bytes":"899365","frames":"70","ns":"23414639496"},"view":{"bytes":"90171991","frames":"753","ns":"19569072761"},"luigi":{"bytes":"2232274","frames":"147","ns":"1621527209"},"fallin'":{"bytes":"1528939","frames":"437","ns":"4764550914"},"sliders":{"bytes":"1428484","frames":"361","ns":"5136830965"},"outro":{"bytes":"24365869","frames":"434","ns":"13007132820"},}}}
