{"notcurses-demo":{"spec":"ixethbcgrwuvlfsjo","TERM":"kitty-direct","rows":"52","cols":"182","runs":{"intro":{"bytes":"18246018","frames":"148","ns":"3027002780"},"xray":{"bytes":"21025595","frames":"302","ns":"5035917739"},"eagle":{"bytes":"24827796","frames":"196","ns":"2539772155"},"trans":{"bytes":"5809708","frames":"629","ns":"16083230992"},"highcon":{"bytes":"387449871","frames":"4641","ns":"7725082083"},"box":{"bytes":"6254973","frames":"51","ns":"3188903509"},"chunli":{"bytes":"1413482","frames":"53","ns":"5402791357"},"grid":{"bytes":"233996985","frames":"768","ns":"4362922125"},"reel":{"bytes":"1665710","frames":"30","ns":"5090993906"},"whiteout":{"bytes":"13472614","frames":"25928","ns":"10002989619"},"uniblock":{"bytes":"962220","frames":"70","ns":"23427133447"},"view":{"bytes":"132546648","frames":"753","ns":"19575036596"},"luigi":{"bytes":"3643970","frames":"215","ns":"1514254159"},"fallin'":{"bytes":"2197677","frames":"501","ns":"5067767780"},"sliders":{"bytes":"2798980","frames":"427","ns":"5267110036"},"outro":{"bytes":"36903531","frames":"434","ns":"13009844893"}}}}
