{"notcurses-demo":{"spec":"ixethbcgrwuvlfsjo","TERM":"kitty-direct","rows":"52","cols":"180","runs":{"intro":{"bytes":"18042600","frames":"148","ns":"3026963335"},"xray":{"bytes":"20883237","frames":"302","ns":"5036052601"},"eagle":{"bytes":"24561100","frames":"195","ns":"2532124414"},"trans":{"bytes":"2686093","frames":"633","ns":"16130484396"},"highcon":{"bytes":"379028767","frames":"4590","ns":"7558465285"},"box":{"bytes":"6193323","frames":"51","ns":"3188208280"},"chunli":{"bytes":"1413396","frames":"53","ns":"5405019771"},"grid":{"bytes":"231546543","frames":"768","ns":"4305399515"},"reel":{"bytes":"1750199","frames":"28","ns":"5006215864"},"whiteout":{"bytes":"13184093","frames":"25826","ns":"10001964727"},"uniblock":{"bytes":"945371","frames":"70","ns":"23427254128"},"view":{"bytes":"131211913","frames":"753","ns":"19574628418"},"luigi":{"bytes":"3611372","frames":"213","ns":"1509529880"},"fallin'":{"bytes":"2243731","frames":"544","ns":"5127354241"},"sliders":{"bytes":"2852708","frames":"445","ns":"5277546608"},"outro":{"bytes":"36372236","frames":"433","ns":"13008687571"}}}}
