{"notcurses-demo":{"spec":"ixethbcgrwuvlfsjo","TERM":"kitty-direct","rows":"52","cols":"148","runs":{"intro":{"bytes":"14756524","frames":"148","ns":"3021648031"},"xray":{"bytes":"18132756","frames":"302","ns":"5035866811"},"eagle":{"bytes":"20482567","frames":"219","ns":"3033302575"},"trans":{"bytes":"5071470","frames":"633","ns":"16143162214"},"highcon":{"bytes":"257278571","frames":"3774","ns":"5198243416"},"box":{"bytes":"5206382","frames":"51","ns":"3156582620"},"chunli":{"bytes":"1412191","frames":"53","ns":"5398535665"},"grid":{"bytes":"192074453","frames":"768","ns":"3271728765"},"reel":{"bytes":"1644620","frames":"33","ns":"5148567891"},"whiteout":{"bytes":"11683451","frames":"35167","ns":"10001196149"},"uniblock":{"bytes":"927614","frames":"70","ns":"23417676290"},"view":{"bytes":"112061281","frames":"753","ns":"19570540707"},"luigi":{"bytes":"2944163","frames":"181","ns":"1525660194"},"fallin'":{"bytes":"1798837","frames":"502","ns":"4920421538"},"sliders":{"bytes":"2291477","frames":"393","ns":"5187923144"},"outro":{"bytes":"30568904","frames":"433","ns":"13007608170"},}}}
