{"notcurses-demo":{"spec":"ixethbcgrwuvlfsjo","TERM":"kitty-direct","rows":"52","cols":"81","runs":{"intro":{"bytes":"5467347","frames":"148","ns":"3018159327"},"xray":{"bytes":"12225804","frames":"302","ns":"5036493962"},"eagle":{"bytes":"11206582","frames":"152","ns":"2741259304"},"trans":{"bytes":"1805163","frames":"633","ns":"16019073748"},"highcon":{"bytes":"76852982","frames":"2065","ns":"1542891556"},"box":{"bytes":"3138876","frames":"51","ns":"3130363995"},"chunli":{"bytes":"1398882","frames":"53","ns":"5395476334"},"grid":{"bytes":"105390666","frames":"768","ns":"1861448758"},"reel":{"bytes":"726856","frames":"28","ns":"5168520815"},"whiteout":{"bytes":"7071869","frames":"65677","ns":"10001001659"},"uniblock":{"bytes":"885075","frames":"70","ns":"23410799931"},"view":{"bytes":"73045023","frames":"753","ns":"19568814079"},"luigi":{"bytes":"1541512","frames":"114","ns":"1850318831"},"fallin'":{"bytes":"1114195","frames":"398","ns":"4646502855"},"sliders":{"bytes":"872596","frames":"332","ns":"5093951499"},"outro":{"bytes":"18612444","frames":"434","ns":"13006695751"},}}}
