{"notcurses-demo":{"spec":"ixethbcgrwuvlfsjo","TERM":"kitty-direct","rows":"52","cols":"136","runs":{"intro":{"bytes":"13353232","frames":"148","ns":"3021715581"},"xray":{"bytes":"17030061","frames":"302","ns":"5035879957"},"eagle":{"bytes":"18813882","frames":"207","ns":"2946227327"},"trans":{"bytes":"1741698","frames":"633","ns":"16077505053"},"highcon":{"bytes":"217761863","frames":"3468","ns":"4314961083"},"box":{"bytes":"4836165","frames":"51","ns":"3151744611"},"chunli":{"bytes":"1411711","frames":"53","ns":"5397839173"},"grid":{"bytes":"176809766","frames":"768","ns":"3091579729"},"reel":{"bytes":"841857","frames":"23","ns":"5253760381"},"whiteout":{"bytes":"11255833","frames":"38331","ns":"10001217209"},"uniblock":{"bytes":"909912","frames":"70","ns":"23413342176"},"view":{"bytes":"104507842","frames":"753","ns":"19569479018"},"luigi":{"bytes":"2691533","frames":"169","ns":"1557198499"},"fallin'":{"bytes":"1779730","frames":"518","ns":"4924705986"},"sliders":{"bytes":"1883453","frames":"389","ns":"5171286333"},"outro":{"bytes":"28525952","frames":"434","ns":"13018574797"},}}}
