{"notcurses-demo":{"spec":"ixethbcgrwuvlfsjo","TERM":"kitty-direct","rows":"52","cols":"114","runs":{"intro":{"bytes":"10484088","frames":"148","ns":"3020092442"},"xray":{"bytes":"14911954","frames":"302","ns":"5035855787"},"eagle":{"bytes":"15743969","frames":"185","ns":"2906572306"},"trans":{"bytes":"3324823","frames":"633","ns":"16074599950"},"highcon":{"bytes":"153706857","frames":"2907","ns":"3123870788"},"box":{"bytes":"4157894","frames":"51","ns":"3151951597"},"chunli":{"bytes":"1411135","frames":"53","ns":"5392672564"},"grid":{"bytes":"147827175","frames":"768","ns":"2747935450"},"reel":{"bytes":"1101195","frames":"29","ns":"5010678353"},"whiteout":{"bytes":"9460949","frames":"43078","ns":"10001154569"},"uniblock":{"bytes":"893620","frames":"70","ns":"23417918058"},"view":{"bytes":"90171933","frames":"753","ns":"19569266883"},"luigi":{"bytes":"2232274","frames":"147","ns":"1627638586"},"fallin'":{"bytes":"1505426","frames":"455","ns":"4936942118"},"sliders":{"bytes":"1435313","frames":"361","ns":"5143433176"},"outro":{"bytes":"24365869","frames":"434","ns":"13007139274"}}}}
