{"notcurses-demo":{"spec":"ixethbcgrwuvlfsjo","TERM":"kitty-direct","rows":"52","cols":"122","runs":{"intro":{"bytes":"11572791","frames":"148","ns":"3020911930"},"xray":{"bytes":"15733503","frames":"302","ns":"5035911028"},"eagle":{"bytes":"16857354","frames":"193","ns":"2877374069"},"trans":{"bytes":"3170240","frames":"633","ns":"16071869361"},"highcon":{"bytes":"175745678","frames":"3111","ns":"3488976933"},"box":{"bytes":"4404502","frames":"51","ns":"3148627699"},"chunli":{"bytes":"1411134","frames":"53","ns":"5398794763"},"grid":{"bytes":"157833240","frames":"768","ns":"2741822732"},"reel":{"bytes":"878485","frames":"32","ns":"5223795617"},"whiteout":{"bytes":"10144976","frames":"43332","ns":"10001181732"},"uniblock":{"bytes":"918301","frames":"70","ns":"23414279909"},"view":{"bytes":"95399845","frames":"753","ns":"19570345268"},"luigi":{"bytes":"2386010","frames":"155","ns":"1594832607"},"fallin'":{"bytes":"1577166","frames":"459","ns":"4890570532"},"sliders":{"bytes":"1855708","frames":"377","ns":"5157797641"},"outro":{"bytes":"25859302","frames":"434","ns":"13017126988"},}}}
