{"notcurses-demo":{"spec":"ixethbcgrwuvlfsjo","TERM":"kitty-direct","rows":"52","cols":"106","runs":{"intro":{"bytes":"9326728","frames":"148","ns":"3020807428"},"xray":{"bytes":"14151531","frames":"302","ns":"5036014285"},"eagle":{"bytes":"14625158","frames":"177","ns":"2857997319"},"trans":{"bytes":"2885642","frames":"633","ns":"16061465016"},"highcon":{"bytes":"133004745","frames":"2703","ns":"2703643048"},"box":{"bytes":"3910034","frames":"51","ns":"3150073660"},"chunli":{"bytes":"1411858","frames":"53","ns":"5398006549"},"grid":{"bytes":"137762855","frames":"768","ns":"2571946872"},"reel":{"bytes":"1067297","frames":"27","ns":"5526054300"},"whiteout":{"bytes":"9056224","frames":"46464","ns":"10001251320"},"uniblock":{"bytes":"895301","frames":"70","ns":"23414172681"},"view":{"bytes":"84694052","frames":"753","ns":"19568665907"},"luigi":{"bytes":"2057555","frames":"139","ns":"1663802075"},"fallin'":{"bytes":"1364451","frames":"432","ns":"4700797203"},"sliders":{"bytes":"1437477","frames":"361","ns":"5135974133"},"outro":{"bytes":"22871807","frames":"434","ns":"13006966981"}}}}
