{"notcurses-demo":{"spec":"ixethbcgrwuvlfsjo","TERM":"vte-256color","rows":"52","cols":"124","runs":{"intro":{"bytes":"9636676","frames":"128","ns":"3020837497"},"xray":{"bytes":"15895682","frames":"302","ns":"5035747618"},"eagle":{"bytes":"17138772","frames":"195","ns":"4385663400"},"trans":{"bytes":"2748881","frames":"633","ns":"16059770780"},"highcon":{"bytes":"181475417","frames":"3162","ns":"10697703473"},"box":{"bytes":"4466251","frames":"51","ns":"3146428726"},"chunli":{"bytes":"1411222","frames":"53","ns":"5387015228"},"grid":{"bytes":"160300995","frames":"768","ns":"6864246205"},"reel":{"bytes":"1639791","frames":"32","ns":"5132591896"},"whiteout":{"bytes":"9807331","frames":"42053","ns":"10001108367"},"uniblock":{"bytes":"888145","frames":"70","ns":"23416250709"},"view":{"bytes":"96702900","frames":"753","ns":"19570350824"},"luigi":{"bytes":"2429873","frames":"157","ns":"2613077019"},"fallin'":{"bytes":"1634289","frames":"496","ns":"4775095894"},"sliders":{"bytes":"1862000","frames":"379","ns":"5516700826"},"jungle":{"bytes":"717152","frames":"701","ns":"5007270641"},"outro":{"bytes":"26271753","frames":"434","ns":"13017432388"},}}}
