{"notcurses-demo":{"spec":"ixethbcgrwuvlfsjo","TERM":"vte-256color","rows":"52","cols":"169","runs":{"intro":{"bytes":"11124232","frames":"110","ns":"3033176190"},"xray":{"bytes":"21246827","frames":"302","ns":"5310360669"},"eagle":{"bytes":"23061648","frames":"188","ns":"4781018018"},"trans":{"bytes":"4804558","frames":"631","ns":"16113863459"},"highcon":{"bytes":"334447464","frames":"4309","ns":"19263835639"},"box":{"bytes":"5854331","frames":"51","ns":"3157449801"},"chunli":{"bytes":"1393323","frames":"53","ns":"5388785150"},"grid":{"bytes":"218093192","frames":"768","ns":"11285001290"},"reel":{"bytes":"1235114","frames":"23","ns":"5234741822"},"whiteout":{"bytes":"12049470","frames":"29979","ns":"10002252471"},"uniblock":{"bytes":"947761","frames":"70","ns":"23423990839"},"view":{"bytes":"140419698","frames":"753","ns":"19573550416"},"luigi":{"bytes":"3378219","frames":"202","ns":"4581328900"},"fallin'":{"bytes":"2152281","frames":"506","ns":"5923897236"},"sliders":{"bytes":"2312814","frames":"401","ns":"5483982356"},"jungle":{"bytes":"769162","frames":"701","ns":"5007093608"},"outro":{"bytes":"31248360","frames":"410","ns":"13069800442"},}}}
