{"notcurses-demo":{"spec":"ixethbcgrwuvlfsjo","TERM":"xterm-256color","rows":"52","cols":"108","runs":{"intro":{"bytes":"6908035","frames":"113","ns":"3021446494"},"xray":{"bytes":"14359741","frames":"302","ns":"5036154527"},"eagle":{"bytes":"14903436","frames":"179","ns":"3724459756"},"trans":{"bytes":"4259634","frames":"633","ns":"16105370768"},"highcon":{"bytes":"138057567","frames":"2754","ns":"28580519984"},"box":{"bytes":"3971583","frames":"51","ns":"3316123709"},"chunli":{"bytes":"1411568","frames":"53","ns":"5415946255"},"grid":{"bytes":"140274573","frames":"768","ns":"17902961151"},"reel":{"bytes":"993064","frames":"25","ns":"5123881104"},"whiteout":{"bytes":"7192417","frames":"37864","ns":"10000952550"},"uniblock":{"bytes":"898760","frames":"70","ns":"23418247318"},"view":{"bytes":"86149156","frames":"753","ns":"19592277322"},"luigi":{"bytes":"2105394","frames":"141","ns":"1669123028"},"fallin'":{"bytes":"1407564","frames":"465","ns":"4692635660"},"sliders":{"bytes":"1435528","frames":"361","ns":"5155735079"},"jungle":{"bytes":"716326","frames":"701","ns":"5007262895"},"outro":{"bytes":"22529459","frames":"430","ns":"13039852373"}}}}
