{"notcurses-demo":{"spec":"ixethbcgrwuvlfsjo","TERM":"xterm-256color","rows":"52","cols":"100","runs":{"intro":{"bytes":"5678250","frames":"108","ns":"3024042015"},"xray":{"bytes":"13512900","frames":"302","ns":"5036022873"},"eagle":{"bytes":"13832772","frames":"171","ns":"3636513663"},"trans":{"bytes":"3396491","frames":"633","ns":"16042264928"},"highcon":{"bytes":"118319883","frames":"2550","ns":"24537789899"},"box":{"bytes":"3724874","frames":"51","ns":"3279179895"},"chunli":{"bytes":"1412901","frames":"53","ns":"5412091863"},"grid":{"bytes":"130172355","frames":"768","ns":"15983121402"},"reel":{"bytes":"1009799","frames":"28","ns":"5425321800"},"whiteout":{"bytes":"6921681","frames":"47383","ns":"10001110799"},"uniblock":{"bytes":"905671","frames":"70","ns":"23413119671"},"view":{"bytes":"80548396","frames":"753","ns":"19581518260"},"luigi":{"bytes":"1929846","frames":"133","ns":"1702252756"},"fallin'":{"bytes":"1353656","frames":"414","ns":"4516185951"},"sliders":{"bytes":"1434152","frames":"361","ns":"5174432377"},"jungle":{"bytes":"699244","frames":"701","ns":"5007285628"},"outro":{"bytes":"21587690","frames":"433","ns":"13030240061"},}}}
