{"notcurses-demo":{"spec":"ixethbcgrwuvlfsjo","TERM":"xterm-256color","rows":"52","cols":"81","runs":{"intro":{"bytes":"5438088","frames":"147","ns":"3015549179"},"xray":{"bytes":"12225804","frames":"302","ns":"5036131375"},"eagle":{"bytes":"11206582","frames":"152","ns":"3230445552"},"trans":{"bytes":"1805163","frames":"633","ns":"16018011452"},"highcon":{"bytes":"76852982","frames":"2065","ns":"16354347416"},"box":{"bytes":"3138876","frames":"51","ns":"3246285904"},"chunli":{"bytes":"1398882","frames":"53","ns":"5409438352"},"grid":{"bytes":"105390666","frames":"768","ns":"12590055435"},"reel":{"bytes":"694781","frames":"28","ns":"5088647500"},"whiteout":{"bytes":"6059417","frames":"58528","ns":"10001000373"},"uniblock":{"bytes":"884318","frames":"70","ns":"23410393482"},"view":{"bytes":"73044935","frames":"753","ns":"19577853520"},"luigi":{"bytes":"1541512","frames":"114","ns":"1861516370"},"fallin'":{"bytes":"1142561","frames":"388","ns":"4596154132"},"sliders":{"bytes":"868945","frames":"329","ns":"5106769118"},"jungle":{"bytes":"688275","frames":"701","ns":"5007265613"},"outro":{"bytes":"18613302","frames":"434","ns":"13024219595"},}}}
