{"notcurses-demo":{"spec":"ixethbcgrwuvlfsjo","TERM":"xterm-256color","rows":"52","cols":"162","runs":{"intro":{"bytes":"6914214","frames":"78","ns":"3036414113"},"xray":{"bytes":"19349984","frames":"302","ns":"5036190122"},"eagle":{"bytes":"22116780","frames":"186","ns":"4201747718"},"trans":{"bytes":"3860791","frames":"633","ns":"16106076886"},"highcon":{"bytes":"307576841","frames":"4131","ns":"67189769928"},"box":{"bytes":"5638047","frames":"51","ns":"3586402598"},"chunli":{"bytes":"1412686","frames":"53","ns":"5410701737"},"grid":{"bytes":"209531690","frames":"768","ns":"26777602936"},"reel":{"bytes":"1608824","frames":"25","ns":"5124546394"},"whiteout":{"bytes":"8160071","frames":"28622","ns":"10001434720"},"uniblock":{"bytes":"947644","frames":"70","ns":"23423668477"},"view":{"bytes":"120577882","frames":"753","ns":"19622875876"},"luigi":{"bytes":"3244961","frames":"195","ns":"1549346948"},"fallin'":{"bytes":"2080340","frames":"466","ns":"4853606314"},"sliders":{"bytes":"2340022","frames":"409","ns":"5242950035"},"jungle":{"bytes":"768804","frames":"701","ns":"5007349760"},"outro":{"bytes":"26231575","frames":"402","ns":"13053551915"},}}}
