{"notcurses-demo":{"spec":"ixethbcgrwuvlfsjo","TERM":"alacritty","rows":"52","cols":"176","runs":{"intro":{"bytes":"420919","frames":"2","ns":"16764562"},"xray":{"bytes":"20522663","frames":"302","ns":"1983761085"},"eagle":{"bytes":"24014463","frames":"193","ns":"1301926425"},"trans":{"bytes":"304502","frames":"9","ns":"8417965"},"highcon":{"bytes":"362480840","frames":"4488","ns":"6787144893"},"box":{"bytes":"6069916","frames":"51","ns":"160451502"},"chunli":{"bytes":"1413213","frames":"53","ns":"80372689"},"grid":{"bytes":"226670188","frames":"768","ns":"4862994281"},"reel":{"bytes":"329656","frames":"2","ns":"10003545"},"whiteout":{"bytes":"167847","frames":"9","ns":"19782620"},"uniblock":{"bytes":"897089","frames":"70","ns":"61976426"},"view":{"bytes":"129070003","frames":"753","ns":"5021654971"},"luigi":{"bytes":"3519796","frames":"209","ns":"150210108"},"fallin'":{"bytes":"2191474","frames":"529","ns":"504567226"},"sliders":{"bytes":"1921602","frames":"201","ns":"111713070"},"jungle":{"bytes":"168932","frames":"1","ns":"13820247"},"outro":{"bytes":"11860756","frames":"243","ns":"1366579913"}}}}
