{"notcurses-demo":{"spec":"ixethbcgrwuvlfsjo","TERM":"alacritty","rows":"52","cols":"173","runs":{"intro":{"bytes":"411553","frames":"2","ns":"17981092"},"xray":{"bytes":"21628951","frames":"302","ns":"2834840043"},"eagle":{"bytes":"23606109","frames":"191","ns":"1112298793"},"trans":{"bytes":"290700","frames":"9","ns":"8585353"},"highcon":{"bytes":"350323043","frames":"4411","ns":"6378946961"},"box":{"bytes":"5977540","frames":"51","ns":"149605670"},"chunli":{"bytes":"1393460","frames":"53","ns":"67459711"},"grid":{"bytes":"222993061","frames":"768","ns":"4582016019"},"reel":{"bytes":"326961","frames":"2","ns":"10079211"},"whiteout":{"bytes":"166658","frames":"9","ns":"18878707"},"uniblock":{"bytes":"893379","frames":"70","ns":"65197829"},"view":{"bytes":"143268273","frames":"753","ns":"6577891856"},"luigi":{"bytes":"3458207","frames":"206","ns":"147302860"},"fallin'":{"bytes":"2197288","frames":"536","ns":"507855212"},"sliders":{"bytes":"1921161","frames":"201","ns":"108142640"},"jungle":{"bytes":"168776","frames":"1","ns":"12377199"},"outro":{"bytes":"13974929","frames":"243","ns":"2112749266"}}}}
