{"notcurses-demo":{"spec":"ixethbcgrwuvlfsjo","TERM":"alacritty","rows":"52","cols":"123","runs":{"intro":{"bytes":"250166","frames":"2","ns":"14784595"},"xray":{"bytes":"16807071","frames":"302","ns":"2471896696"},"eagle":{"bytes":"16995097","frames":"194","ns":"1237068147"},"trans":{"bytes":"215421","frames":"9","ns":"6389464"},"highcon":{"bytes":"178597369","frames":"3136","ns":"3070663462"},"box":{"bytes":"4435428","frames":"51","ns":"119113072"},"chunli":{"bytes":"1391533","frames":"53","ns":"82662064"},"grid":{"bytes":"159087373","frames":"768","ns":"3355253257"},"reel":{"bytes":"244574","frames":"2","ns":"8179140"},"whiteout":{"bytes":"118189","frames":"9","ns":"13866145"},"uniblock":{"bytes":"876327","frames":"70","ns":"55259407"},"view":{"bytes":"106542358","frames":"753","ns":"5350507815"},"luigi":{"bytes":"2416218","frames":"156","ns":"75680774"},"fallin'":{"bytes":"1606528","frames":"429","ns":"350736640"},"sliders":{"bytes":"1356101","frames":"201","ns":"75051134"},"jungle":{"bytes":"116506","frames":"1","ns":"9462976"},"outro":{"bytes":"10131242","frames":"243","ns":"1607055185"}}}}
