{"notcurses-demo":{"spec":"ixethbcgrwuvlfsjo","TERM":"alacritty","rows":"52","cols":"94","runs":{"intro":{"bytes":"147456","frames":"2","ns":"11547855"},"xray":{"bytes":"12873008","frames":"302","ns":"1355549768"},"eagle":{"bytes":"13005509","frames":"165","ns":"946399861"},"trans":{"bytes":"160703","frames":"9","ns":"3791287"},"highcon":{"bytes":"104314938","frames":"2397","ns":"1634759895"},"box":{"bytes":"3539815","frames":"51","ns":"81881695"},"chunli":{"bytes":"1414710","frames":"53","ns":"64759276"},"grid":{"bytes":"122613036","frames":"768","ns":"2312877147"},"reel":{"bytes":"186707","frames":"2","ns":"5666630"},"whiteout":{"bytes":"91907","frames":"9","ns":"10321794"},"uniblock":{"bytes":"887812","frames":"70","ns":"49340632"},"view":{"bytes":"76507035","frames":"753","ns":"3056844221"},"luigi":{"bytes":"1801363","frames":"127","ns":"61546803"},"fallin'":{"bytes":"1259685","frames":"435","ns":"327770598"},"sliders":{"bytes":"680110","frames":"201","ns":"54072819"},"jungle":{"bytes":"98332","frames":"1","ns":"8248065"},"outro":{"bytes":"6896488","frames":"243","ns":"974877293"}}}}
