{"notcurses-demo":{"spec":"ixethbcgrwuvlfsjo","TERM":"alacritty","rows":"52","cols":"117","runs":{"intro":{"bytes":"228869","frames":"2","ns":"12438571"},"xray":{"bytes":"16183938","frames":"302","ns":"2562518545"},"eagle":{"bytes":"16159615","frames":"188","ns":"1151702009"},"trans":{"bytes":"197391","frames":"9","ns":"5525440"},"highcon":{"bytes":"161811185","frames":"2983","ns":"2847475817"},"box":{"bytes":"4250268","frames":"51","ns":"103410243"},"chunli":{"bytes":"1391316","frames":"53","ns":"60970097"},"grid":{"bytes":"151586868","frames":"768","ns":"2981098186"},"reel":{"bytes":"227957","frames":"2","ns":"7062687"},"whiteout":{"bytes":"111892","frames":"9","ns":"13803259"},"uniblock":{"bytes":"886276","frames":"70","ns":"53185182"},"view":{"bytes":"101880666","frames":"753","ns":"5001175930"},"luigi":{"bytes":"2291199","frames":"150","ns":"69638421"},"fallin'":{"bytes":"1512407","frames":"486","ns":"397850100"},"sliders":{"bytes":"1071815","frames":"201","ns":"67503401"},"jungle":{"bytes":"116194","frames":"1","ns":"9418640"},"outro":{"bytes":"9646375","frames":"243","ns":"1626148729"}}}}
