{"notcurses-demo":{"spec":"ixethbcgrwuvlfsjo","TERM":"alacritty","rows":"52","cols":"107","runs":{"intro":{"bytes":"193465","frames":"2","ns":"8285425"},"xray":{"bytes":"15165181","frames":"302","ns":"2479034868"},"eagle":{"bytes":"14768511","frames":"178","ns":"1091097389"},"trans":{"bytes":"183598","frames":"9","ns":"3611660"},"highcon":{"bytes":"135521283","frames":"2728","ns":"2294183336"},"box":{"bytes":"3940653","frames":"51","ns":"97212184"},"chunli":{"bytes":"1391937","frames":"53","ns":"70522626"},"grid":{"bytes":"139019947","frames":"768","ns":"2752975095"},"reel":{"bytes":"209463","frames":"2","ns":"6509918"},"whiteout":{"bytes":"101303","frames":"9","ns":"11377306"},"uniblock":{"bytes":"888648","frames":"70","ns":"51532956"},"view":{"bytes":"94111415","frames":"753","ns":"4933505532"},"luigi":{"bytes":"2073293","frames":"140","ns":"74474444"},"fallin'":{"bytes":"1461069","frames":"491","ns":"386381466"},"sliders":{"bytes":"1071869","frames":"201","ns":"67399765"},"jungle":{"bytes":"115268","frames":"1","ns":"9173943"},"outro":{"bytes":"8823807","frames":"243","ns":"1708142143"}}}}
