{"notcurses-demo":{"spec":"ixethbcgrwuvlfsjo","TERM":"alacritty","rows":"52","cols":"191","runs":{"intro":{"bytes":"461668","frames":"2","ns":"13616148"},"xray":{"bytes":"23185226","frames":"302","ns":"3038203232"},"eagle":{"bytes":"26051227","frames":"202","ns":"1633508745"},"trans":{"bytes":"332915","frames":"9","ns":"9521899"},"highcon":{"bytes":"426643506","frames":"4870","ns":"8435832195"},"box":{"bytes":"6532608","frames":"51","ns":"168973091"},"chunli":{"bytes":"1394326","frames":"53","ns":"68940276"},"grid":{"bytes":"245002983","frames":"768","ns":"5330464985"},"reel":{"bytes":"365322","frames":"2","ns":"10866557"},"whiteout":{"bytes":"180182","frames":"9","ns":"21097234"},"uniblock":{"bytes":"890966","frames":"70","ns":"61625620"},"view":{"bytes":"155777375","frames":"753","ns":"7029890676"},"luigi":{"bytes":"3831959","frames":"224","ns":"165799847"},"fallin'":{"bytes":"2376394","frames":"511","ns":"473434850"},"sliders":{"bytes":"1919162","frames":"201","ns":"115435024"},"jungle":{"bytes":"169712","frames":"1","ns":"15058671"},"outro":{"bytes":"15169344","frames":"243","ns":"2270782532"}}}}
