{"notcurses-demo":{"spec":"ixethbcgrwuvlfsjo","TERM":"xterm-kitty","rows":"52","cols":"123","runs":{"intro":{"bytes":"250166","frames":"2","ns":"5151074"},"xray":{"bytes":"16807071","frames":"302","ns":"1954313319"},"eagle":{"bytes":"16995097","frames":"194","ns":"724779415"},"trans":{"bytes":"215421","frames":"9","ns":"3888800"},"highcon":{"bytes":"178597369","frames":"3136","ns":"3775389057"},"box":{"bytes":"4435428","frames":"51","ns":"106218235"},"chunli":{"bytes":"1391533","frames":"53","ns":"76524080"},"grid":{"bytes":"159087373","frames":"768","ns":"3087536533"},"reel":{"bytes":"244574","frames":"2","ns":"5060978"},"whiteout":{"bytes":"118063","frames":"9","ns":"16586554"},"uniblock":{"bytes":"876129","frames":"70","ns":"53113800"},"view":{"bytes":"106542358","frames":"753","ns":"3729201872"},"luigi":{"bytes":"2416218","frames":"156","ns":"92290257"},"fallin'":{"bytes":"1606528","frames":"429","ns":"324034610"},"sliders":{"bytes":"1356101","frames":"201","ns":"63157192"},"jungle":{"bytes":"116506","frames":"1","ns":"7224593"},"outro":{"bytes":"10131242","frames":"243","ns":"1363206635"}}}}
