{"notcurses-demo":{"spec":"ixethbcgrwuvlfsjo","TERM":"xterm-kitty","rows":"52","cols":"99","runs":{"intro":{"bytes":"165109","frames":"2","ns":"6722205"},"xray":{"bytes":"14262063","frames":"302","ns":"1820689719"},"eagle":{"bytes":"13698826","frames":"170","ns":"639716106"},"trans":{"bytes":"174957","frames":"9","ns":"3042564"},"highcon":{"bytes":"115940683","frames":"2524","ns":"2460473593"},"box":{"bytes":"3693946","frames":"51","ns":"89919138"},"chunli":{"bytes":"1393333","frames":"53","ns":"77589936"},"grid":{"bytes":"128912248","frames":"768","ns":"2522362243"},"reel":{"bytes":"196023","frames":"2","ns":"10323660"},"whiteout":{"bytes":"96115","frames":"9","ns":"12445466"},"uniblock":{"bytes":"887707","frames":"70","ns":"51132286"},"view":{"bytes":"87712625","frames":"753","ns":"3266053688"},"luigi":{"bytes":"1916556","frames":"132","ns":"72578071"},"fallin'":{"bytes":"1368448","frames":"439","ns":"320591189"},"sliders":{"bytes":"1071191","frames":"201","ns":"49593854"},"jungle":{"bytes":"98592","frames":"1","ns":"7225860"},"outro":{"bytes":"8221643","frames":"243","ns":"1310635255"}}}}
