{"notcurses-demo":{"spec":"ixethbcgrwuvlfsjo","TERM":"vte-256color","rows":"52","cols":"83","runs":{"intro":{"bytes":"107801","frames":"2","ns":"5266011"},"xray":{"bytes":"12447264","frames":"302","ns":"3957203072"},"eagle":{"bytes":"11482459","frames":"154","ns":"1431310263"},"trans":{"bytes":"148770","frames":"9","ns":"3383787"},"highcon":{"bytes":"80789718","frames":"2116","ns":"3942865139"},"box":{"bytes":"3200419","frames":"51","ns":"218995569"},"chunli":{"bytes":"1399403","frames":"53","ns":"150747268"},"grid":{"bytes":"107885869","frames":"768","ns":"6500837701"},"reel":{"bytes":"161438","frames":"2","ns":"5260495"},"whiteout":{"bytes":"81367","frames":"9","ns":"9391693"},"uniblock":{"bytes":"888966","frames":"70","ns":"250995289"},"view":{"bytes":"74690312","frames":"753","ns":"7306795706"},"luigi":{"bytes":"1573363","frames":"116","ns":"131174296"},"fallin'":{"bytes":"1093073","frames":"421","ns":"668729498"},"sliders":{"bytes":"679409","frames":"201","ns":"83156563"},"jungle":{"bytes":"87773","frames":"1","ns":"28976849"},"outro":{"bytes":"6937344","frames":"243","ns":"2966451264"}}}}
