{"notcurses-demo":{"spec":"ixethbcgrwuvlfsjo","TERM":"xterm","rows":"52","cols":"116","runs":{"intro":{"bytes":"224967","frames":"2","ns":"32406948"},"xray":{"bytes":"15160166","frames":"302","ns":"2913132120"},"eagle":{"bytes":"16018227","frames":"187","ns":"2415169631"},"trans":{"bytes":"200806","frames":"9","ns":"34006709"},"highcon":{"bytes":"159088801","frames":"2958","ns":"17728278076"},"box":{"bytes":"4219445","frames":"51","ns":"506646457"},"chunli":{"bytes":"1411061","frames":"53","ns":"312768508"},"grid":{"bytes":"150337405","frames":"768","ns":"10542052541"},"reel":{"bytes":"230300","frames":"2","ns":"29151279"},"whiteout":{"bytes":"112058","frames":"9","ns":"48383396"},"uniblock":{"bytes":"882769","frames":"70","ns":"234180844"},"view":{"bytes":"91456912","frames":"753","ns":"10039995185"},"luigi":{"bytes":"2254179","frames":"149","ns":"404854673"},"fallin'":{"bytes":"1536968","frames":"447","ns":"1222156990"},"sliders":{"bytes":"1071253","frames":"201","ns":"372314344"},"outro":{"bytes":"8267831","frames":"243","ns":"1929248833"}}}}
